love_protocol/__init__.py
love_protocol/constants.py
love_protocol/py.typed
love_protocol/cli/__init__.py
love_protocol/cli/validate.py
love_protocol/core/__init__.py
love_protocol/core/decode.py
love_protocol/core/encode.py
love_protocol/core/error.py
love_protocol/core/validate.py
love_protocol/handler/__init__.py
love_protocol/handler/handler.py
love_protocol/session/__init__.py
love_protocol/session/middleware.py
love_protocol/session/model.py
love_protocol/session/store.py
love_protocol/types/__init__.py
love_protocol/types/audio_chunk.py
love_protocol/types/audio_start.py
love_protocol/types/audio_stop.py
love_protocol/types/command.py
love_protocol/types/error.py
love_protocol/types/hello.py
love_protocol/types/hello_ack.py
love_protocol/types/intent_detected.py
love_protocol/types/love_message.py
love_protocol/types/media_control.py
love_protocol/types/media_play.py
love_protocol/types/sensor_event.py
love_protocol/types/transcription.py
love_protocol/types/tts_output.py
love_protocol/types/wakeword_detected.py
love_protocol-0.3.2.dist-info/METADATA
love_protocol-0.3.2.dist-info/WHEEL
love_protocol-0.3.2.dist-info/entry_points.txt
love_protocol-0.3.2.dist-info/RECORD
