Metadata-Version: 2.4
Name: love-protocol
Version: 0.3.2
Summary: Python implementation of the LOVE protocol based on JSON schemas
Author-email: Lucy Assistant <dev@lucy-assistant.com>
Requires-Python: >=3.10
Requires-Dist: cachetools
Requires-Dist: datamodel-code-generator>=0.25
Requires-Dist: pydantic<2.0
Requires-Dist: pytest-asyncio
